ppbamboo/__init__.py
ppbamboo/__version__.py
ppbamboo/bamboohr.py
ppbamboo-1.1.0.dist-info/LICENSE.txt
ppbamboo-1.1.0.dist-info/METADATA
ppbamboo-1.1.0.dist-info/WHEEL
ppbamboo-1.1.0.dist-info/top_level.txt
ppbamboo-1.1.0.dist-info/RECORD
