Metadata-Version: 2.1
Name: ppbamboo
Version: 1.1.0
Summary: PP's BambooHR Module
Home-page: https://github.com/peterpakos/ppbamboo
Author: Peter Pakos
Author-email: peter.pakos@wandisco.com
License: GPLv3
Keywords: bamboo hr
Platform: UNKNOWN
Classifier: Programming Language :: Python :: 2
Classifier: Programming Language :: Python :: 2.7
Classifier: Programming Language :: Python :: 3
Classifier: Programming Language :: Python :: 3.4
Classifier: Programming Language :: Python :: 3.5
Classifier: Programming Language :: Python :: 3.6
Classifier: Programming Language :: Python :: 3.7
Classifier: License :: OSI Approved :: GNU General Public License v3 (GPLv3)
